TensorflowShenduXuexiShizhanZhinanZhongwenbanChuyi/README.md
TensorflowShenduXuexiShizhanZhinanZhongwenbanChuyi/__init__.py
TensorflowShenduXuexiShizhanZhinanZhongwenbanChuyi/__main__.py
TensorflowShenduXuexiShizhanZhinanZhongwenbanChuyi/file.epub
TensorflowShenduXuexiShizhanZhinanZhongwenbanChuyi/index.html
TensorflowShenduXuexiShizhanZhinanZhongwenbanChuyi/css/__init__.py
TensorflowShenduXuexiShizhanZhinanZhongwenbanChuyi/css/annotations.css
TensorflowShenduXuexiShizhanZhinanZhongwenbanChuyi/css/main.css
TensorflowShenduXuexiShizhanZhinanZhongwenbanChuyi/css/normalize.css
TensorflowShenduXuexiShizhanZhinanZhongwenbanChuyi/css/popup.css
TensorflowShenduXuexiShizhanZhinanZhongwenbanChuyi/font/__init__.py
TensorflowShenduXuexiShizhanZhinanZhongwenbanChuyi/font/fontello.eot
TensorflowShenduXuexiShizhanZhinanZhongwenbanChuyi/font/fontello.svg
TensorflowShenduXuexiShizhanZhinanZhongwenbanChuyi/font/fontello.ttf
TensorflowShenduXuexiShizhanZhinanZhongwenbanChuyi/font/fontello.woff
TensorflowShenduXuexiShizhanZhinanZhongwenbanChuyi/img/__init__.py
TensorflowShenduXuexiShizhanZhinanZhongwenbanChuyi/img/annotator-glyph-sprite.png
TensorflowShenduXuexiShizhanZhinanZhongwenbanChuyi/img/annotator-icon-sprite.png
TensorflowShenduXuexiShizhanZhinanZhongwenbanChuyi/img/apple-touch-icon.png
TensorflowShenduXuexiShizhanZhinanZhongwenbanChuyi/img/cancelfullscreen.png
TensorflowShenduXuexiShizhanZhinanZhongwenbanChuyi/img/close.png
TensorflowShenduXuexiShizhanZhinanZhongwenbanChuyi/img/fullscreen.png
TensorflowShenduXuexiShizhanZhinanZhongwenbanChuyi/img/loader.gif
TensorflowShenduXuexiShizhanZhinanZhongwenbanChuyi/img/menu-icon.png
TensorflowShenduXuexiShizhanZhinanZhongwenbanChuyi/img/save.png
TensorflowShenduXuexiShizhanZhinanZhongwenbanChuyi/img/saved.png
TensorflowShenduXuexiShizhanZhinanZhongwenbanChuyi/img/settings-s.png
TensorflowShenduXuexiShizhanZhinanZhongwenbanChuyi/img/settings.png
TensorflowShenduXuexiShizhanZhinanZhongwenbanChuyi/img/star.png
tensorflow_shendu_xuexi_shizhan_zhinan_zhongwenban_chuyi-2024.3.5.0.dist-info/METADATA
tensorflow_shendu_xuexi_shizhan_zhinan_zhongwenban_chuyi-2024.3.5.0.dist-info/WHEEL
tensorflow_shendu_xuexi_shizhan_zhinan_zhongwenban_chuyi-2024.3.5.0.dist-info/entry_points.txt
tensorflow_shendu_xuexi_shizhan_zhinan_zhongwenban_chuyi-2024.3.5.0.dist-info/top_level.txt
tensorflow_shendu_xuexi_shizhan_zhinan_zhongwenban_chuyi-2024.3.5.0.dist-info/RECORD
